{
  "dependencies": {
    "mssql1": {
      "type": "mssql.local",
      "connectionId": "DefaultConnection"
    },
    "appInsights1": {
      "type": "appInsights.sdk",
      "connectionId": null
    },
    "mssql2": {
      "type": "mssql.local",
      "connectionId": "PrincipalContext"
    },
    "secrets1": {
      "type": "secrets.user"
    },
    "mssql3": {
      "type": "mssql.local",
      "connectionId": "DietaContext"
    },
    "mssql4": {
      "type": "mssql.local",
      "connectionId": "NivelContext"
    },
    "mssql5": {
      "type": "mssql.local",
      "connectionId": "ProgresoContext"
    },
    "mssql6": {
      "type": "mssql.local",
      "connectionId": "RutinaContext"
    }
  }
}